Metadata-Version: 2.1
Name: sequenoscope
Version: 0.0.5
Summary: Description
Home-page: https://github.com/phac-nml/sequenoscope
Author: Abdallah Meknas
Author-email: abdallah.meknas@phac-aspc.gc.ca
License: GPLv3
Keywords: Keywords
Classifier: Development Status :: 3 - Alpha
Classifier: Environment :: Console
Classifier: License :: OSI Approved :: GNU General Public License v3 or later (GPLv3+)
Classifier: Intended Audience :: Science/Research
Classifier: Topic :: Scientific/Engineering
Classifier: Topic :: Scientific/Engineering :: Bio-Informatics
Classifier: Programming Language :: Python
Classifier: Programming Language :: Python :: 3.7
Classifier: Programming Language :: Python :: Implementation :: CPython
Classifier: Operating System :: POSIX :: Linux
Requires-Python: >=3.7.0
License-File: LICENSE
Requires-Dist: biopython
Requires-Dist: numpy
Requires-Dist: pandas (>=1.5)
Requires-Dist: plotly
Requires-Dist: psutil
Requires-Dist: pysam
Requires-Dist: pytest
Requires-Dist: scipy
Requires-Dist: seqtk
Requires-Dist: simplejson
Requires-Dist: six
